CODE_OF_CONDUCT.md
CONTRIBUTING.md
MANIFEST.in
README.md
RELEASE_NOTES.md
requirements-test.txt
requirements.txt
setup.cfg
setup.py
iddex/__init__.py
iddex/account.py
iddex/amount.py
iddex/asset.py
iddex/block.py
iddex/blockchain.py
iddex/blockchainobject.py
iddex/committee.py
iddex/dex.py
iddex/exceptions.py
iddex/genesisbalance.py
iddex/htlc.py
iddex/iddex.py
iddex/instance.py
iddex/market.py
iddex/memo.py
iddex/message.py
iddex/notify.py
iddex/price.py
iddex/proposal.py
iddex/storage.py
iddex/transactionbuilder.py
iddex/utils.py
iddex/vesting.py
iddex/wallet.py
iddex/witness.py
iddex/worker.py
iddex.egg-info/PKG-INFO
iddex.egg-info/SOURCES.txt
iddex.egg-info/dependency_links.txt
iddex.egg-info/requires.txt
iddex.egg-info/top_level.txt
iddexapi/__init__.py
iddexapi/exceptions.py
iddexapi/iddexnoderpc.py
iddexapi/websocket.py
iddexbase/__init__.py
iddexbase/account.py
iddexbase/asset_permissions.py
iddexbase/bip38.py
iddexbase/chains.py
iddexbase/memo.py
iddexbase/objects.py
iddexbase/objecttypes.py
iddexbase/operationids.py
iddexbase/operations.py
iddexbase/signedtransactions.py
iddexbase/transactions.py