Metadata-Version: 1.2
Name: iddex
Version: 0.3.7
Summary: Python library for iddex
Home-page: https://gitlab.com/id.dex-pub/python-iddex
Author: Graham Rogen
Author-email: grogen@id-chain.org
Maintainer: Graham Rogen
Maintainer-email: grogen@id-chain.org
License: UNKNOWN
Download-URL: https://gitlab.com/id.dex-pub/python-iddex/tarball/0.3.7 
Keywords: iddex,library,api,rpc
Platform: UNKNOWN
Classifier: License :: OSI Approved :: MIT License
Classifier: Operating System :: OS Independent
Classifier: Programming Language :: Python :: 3
Classifier: Development Status :: 3 - Alpha
Classifier: Intended Audience :: Developers
Classifier: Intended Audience :: Financial and Insurance Industry
Classifier: Topic :: Office/Business :: Financial
